Metadata-Version: 1.0
Name: fuck996
Version: 0.0.1
Summary: a library for 996
Home-page: UNKNOWN
Author: 068089dy@gmail.com
Author-email: UNKNOWN
License: Anti996 License
Keywords: fuck 996
Platform: any
